{
	"@type":"Hierarchy",
	"Name":"LogFileList.txt",
	"Elements":
	[
		{
			"Name":"c:\\ibm\\cognos\\tm1_64\\samples\\tm1\\24Retail\\data\\tm1event.log",
			"Type":"Numeric"
		},
		{
			"Name":"c:\\ibm\\cognos\\tm1_64\\samples\\tm1\\24Retail\\data\\tm1s20170901195521.log",
			"Type":"Numeric"
		},
		{
			"Name":"c:\\ibm\\cognos\\tm1_64\\samples\\tm1\\24Retail\\data\\tm1s20170913203237.log",
			"Type":"Numeric"
		},
		{
			"Name":"c:\\ibm\\cognos\\tm1_64\\samples\\tm1\\24Retail\\data\\tm1s20170914143727.log",
			"Type":"Numeric"
		},
		{
			"Name":"c:\\ibm\\cognos\\tm1_64\\samples\\tm1\\24Retail\\data\\tm1server.log",
			"Type":"Numeric"
		},
		{
			"Name":"c:\\ibm\\cognos\\tm1_64\\samples\\tm1\\24Retail\\logs\\tm1event.log",
			"Type":"Numeric"
		},
		{
			"Name":"c:\\ibm\\cognos\\tm1_64\\samples\\tm1\\24Retail\\logs\\tm1s.log",
			"Type":"Numeric"
		},
		{
			"Name":"c:\\ibm\\cognos\\tm1_64\\samples\\tm1\\24Retail\\logs\\tm1s20190510001600.log",
			"Type":"Numeric"
		},
		{
			"Name":"c:\\ibm\\cognos\\tm1_64\\samples\\tm1\\24Retail\\logs\\tm1s20190510011657.log",
			"Type":"Numeric"
		},
		{
			"Name":"c:\\ibm\\cognos\\tm1_64\\samples\\tm1\\24Retail\\logs\\tm1s20190516182312.log",
			"Type":"Numeric"
		},
		{
			"Name":"c:\\ibm\\cognos\\tm1_64\\samples\\tm1\\24Retail\\logs\\tm1s20190518212222.log",
			"Type":"Numeric"
		},
		{
			"Name":"c:\\ibm\\cognos\\tm1_64\\samples\\tm1\\24Retail\\logs\\tm1server.log",
			"Type":"Numeric"
		},
		{
			"Name":"c:\\ibm\\cognos\\tm1_64\\samples\\tm1\\GO_New_Stores\\logfiles\\tm1event.log",
			"Type":"Numeric"
		},
		{
			"Name":"c:\\ibm\\cognos\\tm1_64\\samples\\tm1\\GO_New_Stores\\logfiles\\tm1s.log",
			"Type":"Numeric"
		},
		{
			"Name":"c:\\ibm\\cognos\\tm1_64\\samples\\tm1\\GO_New_Stores\\logfiles\\tm1s20190510001505.log",
			"Type":"Numeric"
		},
		{
			"Name":"c:\\ibm\\cognos\\tm1_64\\samples\\tm1\\GO_New_Stores\\logfiles\\tm1s20190510011600.log",
			"Type":"Numeric"
		},
		{
			"Name":"c:\\ibm\\cognos\\tm1_64\\samples\\tm1\\GO_New_Stores\\logfiles\\tm1s20190516182311.log",
			"Type":"Numeric"
		},
		{
			"Name":"c:\\ibm\\cognos\\tm1_64\\samples\\tm1\\GO_New_Stores\\logfiles\\tm1server.log",
			"Type":"Numeric"
		},
		{
			"Name":"c:\\ibm\\cognos\\tm1_64\\samples\\tm1\\GO_scorecards\\logfiles\\tm1event.log",
			"Type":"Numeric"
		},
		{
			"Name":"c:\\ibm\\cognos\\tm1_64\\samples\\tm1\\GO_scorecards\\logfiles\\tm1s.log",
			"Type":"Numeric"
		},
		{
			"Name":"c:\\ibm\\cognos\\tm1_64\\samples\\tm1\\GO_scorecards\\logfiles\\tm1s20190510001502.log",
			"Type":"Numeric"
		},
		{
			"Name":"c:\\ibm\\cognos\\tm1_64\\samples\\tm1\\GO_scorecards\\logfiles\\tm1s20190510011556.log",
			"Type":"Numeric"
		},
		{
			"Name":"c:\\ibm\\cognos\\tm1_64\\samples\\tm1\\GO_scorecards\\logfiles\\tm1s20190516182308.log",
			"Type":"Numeric"
		},
		{
			"Name":"c:\\ibm\\cognos\\tm1_64\\samples\\tm1\\GO_scorecards\\logfiles\\tm1server.log",
			"Type":"Numeric"
		},
		{
			"Name":"c:\\ibm\\cognos\\tm1_64\\samples\\tm1\\PlanSamp\\tm1event.log",
			"Type":"Numeric"
		},
		{
			"Name":"c:\\ibm\\cognos\\tm1_64\\samples\\tm1\\PlanSamp\\TM1ProcessError_20190521221819_24741732_test.log",
			"Type":"Numeric"
		},
		{
			"Name":"c:\\ibm\\cognos\\tm1_64\\samples\\tm1\\PlanSamp\\TM1ProcessError_20190521222013_11809968_test.log",
			"Type":"Numeric"
		},
		{
			"Name":"c:\\ibm\\cognos\\tm1_64\\samples\\tm1\\PlanSamp\\TM1ProcessError_20190521230046_61635080_test.log",
			"Type":"Numeric"
		},
		{
			"Name":"c:\\ibm\\cognos\\tm1_64\\samples\\tm1\\PlanSamp\\TM1ProcessError_20190522013330_28523316_Get files.log",
			"Type":"Numeric"
		},
		{
			"Name":"c:\\ibm\\cognos\\tm1_64\\samples\\tm1\\PlanSamp\\TM1ProcessError_20190522014951_08325540_Get files.log",
			"Type":"Numeric"
		},
		{
			"Name":"c:\\ibm\\cognos\\tm1_64\\samples\\tm1\\PlanSamp\\tm1s.log",
			"Type":"Numeric"
		},
		{
			"Name":"c:\\ibm\\cognos\\tm1_64\\samples\\tm1\\PlanSamp\\tm1s20190510001606.log",
			"Type":"Numeric"
		},
		{
			"Name":"c:\\ibm\\cognos\\tm1_64\\samples\\tm1\\PlanSamp\\tm1s20190510005019.log",
			"Type":"Numeric"
		},
		{
			"Name":"c:\\ibm\\cognos\\tm1_64\\samples\\tm1\\PlanSamp\\tm1s20190510011706.log",
			"Type":"Numeric"
		},
		{
			"Name":"c:\\ibm\\cognos\\tm1_64\\samples\\tm1\\PlanSamp\\tm1s20190514181915.log",
			"Type":"Numeric"
		},
		{
			"Name":"c:\\ibm\\cognos\\tm1_64\\samples\\tm1\\PlanSamp\\tm1s20190516182306.log",
			"Type":"Numeric"
		},
		{
			"Name":"c:\\ibm\\cognos\\tm1_64\\samples\\tm1\\PlanSamp\\tm1s20190520144021.log",
			"Type":"Numeric"
		},
		{
			"Name":"c:\\ibm\\cognos\\tm1_64\\samples\\tm1\\PlanSamp\\tm1s20190520145359.log",
			"Type":"Numeric"
		},
		{
			"Name":"c:\\ibm\\cognos\\tm1_64\\samples\\tm1\\PlanSamp\\tm1s20190520150057.log",
			"Type":"Numeric"
		},
		{
			"Name":"c:\\ibm\\cognos\\tm1_64\\samples\\tm1\\PlanSamp\\tm1server.log",
			"Type":"Numeric"
		},
		{
			"Name":"c:\\ibm\\cognos\\tm1_64\\samples\\tm1\\PlanSamp\\tm1top.log",
			"Type":"Numeric"
		},
		{
			"Name":"c:\\ibm\\cognos\\tm1_64\\samples\\tm1\\PlanSamp\\model_upload\\tm1server.log",
			"Type":"Numeric"
		},
		{
			"Name":"c:\\ibm\\cognos\\tm1_64\\samples\\tm1\\Proven_Techniques\\logfiles\\tm1event.log",
			"Type":"Numeric"
		},
		{
			"Name":"c:\\ibm\\cognos\\tm1_64\\samples\\tm1\\Proven_Techniques\\logfiles\\tm1s.log",
			"Type":"Numeric"
		},
		{
			"Name":"c:\\ibm\\cognos\\tm1_64\\samples\\tm1\\Proven_Techniques\\logfiles\\tm1s20190510001459.log",
			"Type":"Numeric"
		},
		{
			"Name":"c:\\ibm\\cognos\\tm1_64\\samples\\tm1\\Proven_Techniques\\logfiles\\tm1s20190510011553.log",
			"Type":"Numeric"
		},
		{
			"Name":"c:\\ibm\\cognos\\tm1_64\\samples\\tm1\\Proven_Techniques\\logfiles\\tm1s20190516182304.log",
			"Type":"Numeric"
		},
		{
			"Name":"c:\\ibm\\cognos\\tm1_64\\samples\\tm1\\Proven_Techniques\\logfiles\\tm1server.log",
			"Type":"Numeric"
		},
		{
			"Name":"c:\\ibm\\cognos\\tm1_64\\samples\\tm1\\Rules_Guide_Data\\tm1serr.log",
			"Type":"Numeric"
		},
		{
			"Name":"c:\\ibm\\cognos\\tm1_64\\samples\\tm1\\SData\\tm1event.log",
			"Type":"Numeric"
		},
		{
			"Name":"c:\\ibm\\cognos\\tm1_64\\samples\\tm1\\SData\\tm1s.log",
			"Type":"Numeric"
		},
		{
			"Name":"c:\\ibm\\cognos\\tm1_64\\samples\\tm1\\SData\\tm1s20190510001603.log",
			"Type":"Numeric"
		},
		{
			"Name":"c:\\ibm\\cognos\\tm1_64\\samples\\tm1\\SData\\tm1s20190510011701.log",
			"Type":"Numeric"
		},
		{
			"Name":"c:\\ibm\\cognos\\tm1_64\\samples\\tm1\\SData\\tm1s20190516182302.log",
			"Type":"Numeric"
		},
		{
			"Name":"c:\\ibm\\cognos\\tm1_64\\samples\\tm1\\SData\\tm1server.log",
			"Type":"Numeric"
		},
		{
			"Name":"c:\\ibm\\cognos\\tm1_64\\samples\\tm1\\PlanSamp\\TM1ProcessError_20190522122142_09125032_test.log",
			"Type":"Numeric"
		},
		{
			"Name":"c:\\ibm\\cognos\\tm1_64\\samples\\tm1\\PlanSamp\\TM1ProcessError_20190522122623_33816248_test.log",
			"Type":"Numeric"
		}
	],
	"Subsets@Code.links":[]
}